{
  "todos": [
    {
      "id": 1,
      "name": "Setup Server",
      "isComplete": true
    },
    {
      "id": 2,
      "name": "Start Server",
      "isComplete": false
    },
    {
      "id": 3,
      "name": "Connect to Server",
      "isComplete": false
    },
    {
      "id": 5907,
      "name": "Setup Fetch",
      "isComplete": false
    }
  ],
  "compliance": [],
  "history": [
    {
      "cmd": "ls",
      "system": false,
      "id": 1
    },
    {
      "cmd": "go compliance",
      "system": false,
      "id": 2
    },
    {
      "cmd": "test",
      "system": false,
      "id": "308ce2ca-95ec-4acf-a6b2-a9c633e29191"
    },
    {
      "cmd": "go home",
      "system": false,
      "id": "1a0ce314-d0d7-4766-8418-c3af1223c067"
    },
    {
      "cmd": "test",
      "system": false,
      "id": "27b55c0a-e0fb-4028-b3c5-a0d21231bbc3"
    },
    {
      "cmd": "new compliance",
      "system": false,
      "id": "96a13ca1-adc2-473b-8685-bbaaf3020a4a"
    },
    {
      "cmd": "new compliance",
      "system": false,
      "id": "9d400ab9-353c-491b-90ff-1ae9eb3cea69"
    },
    {
      "cmd": "new compliance",
      "system": false,
      "id": "441dd8c9-98f9-49b8-9650-72443ec829df"
    },
    {
      "cmd": "new compliance",
      "system": false,
      "id": "50610623-8079-43fd-9653-22b39c133a9c"
    },
    {
      "cmd": "new compliance",
      "system": false,
      "id": "d4939055-9feb-40ba-bef7-901a5c1bb991"
    },
    {
      "cmd": "add compliance",
      "system": false,
      "id": "db4bb755-0832-4910-90a2-c131bb4df054"
    }
  ]
}